	<string id="bar_bring_hunter_rifle">
		<text>Повернути мисливцеві фамільну рушницю</text>
	</string>
	<string id="bar_bring_pda_lucky">
		<text>Принести КПК лідера Барменові</text>
	</string>
	<string id="bar_crazy_veterans_quest">
		<text>Знищити божевільних ветеранів</text>
	</string>
	<string id="bar_dolg_test_quest">
		<text>Перевірка для вступу в Долг</text>
	</string>
	<string id="bar_dolg_bring_document">
		<text>Знайти в ангарі архівні документи та принести їх капітанові Іванцову.</text>
	</string>
	<string id="bar_dolg_base_rules">
		<text>Відмітитися в начальника охорони «Долгу»</text>
	</string>
	<string id="bar_dolg_base_rules_fin">
		<text>Повернутися до Бармена</text>
	</string>
	<string id="bar_dolg_base_rules_talk">
		<text>Знайти начальника охорони «Долгу» і відмітитися в нього</text>
	</string>
	<string id="bar_dolg_bring_rg6">
		<text>Здобути «Бульдог-6» для генерала Вороніна</text>
	</string>
	<string id="bar_dolg_community_quest">
		<text>Вступ до угруповання «Долг»</text>
	</string>
	<string id="bar_dolg_community_quest_prisyaga">
		<text>Прийняти присягу</text>
	</string>
	<string id="bar_dolg_community_quest_recomendation">
		<text>Отримати рекомендацію капітана Іванцова</text>
	</string>
	<string id="bar_dolg_community_quest_vernost">
		<text>Довести свою вірність «Долгу»</text>
	</string>
	<string id="bar_dolg_find_cook">
		<text>Увійти в довіру до кухаря «Волі» й довідатися, де зберігається «Бульдог-6»</text>
	</string>
	<string id="bar_dolg_find_rg6">
		<text>Проникнути на територію угруповання «Волі», знайти і вкрасти «Бульдог-6»</text>
	</string>
	<string id="bar_dolg_info_gain">
		<text>Знайти перехоплену інформацію про лабораторію X-18</text>
	</string>
	<string id="bar_dolg_kill_tiran">
		<text>Убити Тирана, проводиря загону</text>
	</string>
	<string id="bar_dolg_return_info">
		<text>Повернути інформацію про лабораторію X-18 генералові Вороніну</text>
	</string>
	<string id="bar_dolg_return_rg6">
		<text>Принести «Бульдог-6» генералові Вороніну</text>
	</string>
	<string id="bar_dolg_rg6_quest">
		<text>Завдання для вступу до угруповання «Долг»</text>
	</string>
	<string id="bar_dolg_svoboda_ambush_quest">
		<text>Знищити найманців</text>
	</string>
	<string id="bar_dolg_svoboda_ambush_return">
		<text>Віддати нашивки генералові Вороніну</text>
	</string>
	<string id="bar_dolg_tiran_PDA">
		<text>Узяти КПК Тирана</text>
	</string>
	<string id="bar_dolg_svoboda_leader_kill_quest">
		<text>Знищення лідера угруповання Волі</text>
	</string>
	<string id="mil_svoboda_leader_kill">
		<text>На території Військової бази знайти та знищити лідера угруповання Воля</text>
	</string>
	<string id="mil_svoboda_leader_stripe">
		<text>Забрати особисті речі Лідера як доказ його смерті</text>
	</string>
	<string id="bar_dolg_svoboda_leader_kill_return">
		<text>Повернутися до генерала Вороніна з речами Лідера Волі</text>
	</string>
	<string id="bar_hunter_find_rifle">
		<text>Знайти фамільну рушницю</text>
	</string>
	<string id="bar_hunter_return_rifle">
		<text>Повернути рушницю мисливцеві у Барі</text>
	</string>
	<string id="bar_hunter_rifle">
		<text>Знайти фамільну рушницю</text>
	</string>
	<string id="bar_kill_crazy_veterans">
		<text>Убити лідера ветеранів</text>
	</string>
	<string id="bar_kill_crazy_veterans_pda">
		<text>Узяти КПК лідера</text>
	</string>
	<string id="bar_kill_veterans">
		<text>Знищити табір божевільних ветеранів</text>
	</string>
	<string id="bar_radar_deactivate">
		<text>Відключити Випалювач Мізків</text>
	</string>
	<string id="bar_resque_information">
		<text>Зустрітися із Кругловим</text>
	</string>
	<string id="bar_resque_information_2">
		<text>Вивести Круглова на Янтар</text>
	</string>
	<string id="bar_resque_scientific_follow">
		<text>Вивести Круглова до виходу на Янтар</text>
	</string>
	<string id="bar_resque_scientific_information">
		<text>...</text>
	</string>
	<string id="bar_resque_scientific_information_bring">
		<text>Поговорити із Кругловим</text>
	</string>
	<string id="bar_resque_scientific_information_get">
		<text>Пробитися до Круглова</text>
	</string>
	<string id="bar_resque_scientific_information_get_2">
		<text>Поговорити із професором Кругловим</text>
	</string>
	<string id="bar_x16_documents">
		<text>Знайти документи у лабораторії X-16</text>
	</string>
	<string id="bring_x16_documents">
		<text>Принести документи Барменові</text>
	</string>
	<string id="deactivate_radar_now">
		<text>Відключити установку</text>
	</string>
	<string id="find_and_deactivate_radar">
		<text>Знайти вхід до бункера управління</text>
	</string>
	<string id="get_to_antennas">
		<text>Дістатися антен</text>
	</string>
	<string id="Kruglov_research">
		<text>Дослідження Круглова</text>
	</string>
	<string id="look_for_x16_lab">
		<text>Знайти документи з Х-16</text>
	</string>
	<string id="wpn-winchester_m1">
		<text>Бойовий Чейзер</text>
	</string>
	<string id="x16_yantar">
		<text>Поговорити з ученими</text>
	</string>
	<string id="give_documents_on_decoding">
		<text>Віддати вченим документи на розшифровку</text>
	</string>
	<string id="take_decoding_documents">
		<text>Забрати розшифровані документи</text>
	</string>
	<string id="bring_decoding_documents">
		<text>Принести розшифровані документи Бармену</text>
	</string>
    <string id="ros_help_svoboda_receive_info">
        <text>Допомога Волі.</text>
    </string>
    <string id="ros_help_svoboda_receive_info_0">
         <text>Допомогти Волі отримати результати дослідження вчених.</text>
    </string>
    <string id="ros_help_svoboda_receive_info_1">
         <text>Допомогти Волі отримати результати досліджень професора Круглова.</text>
    </string>
	<string id="bar_ryaboy_job">
		<text>Зустріч із психом</text>
	</string>
	<string id="bar_ryaboy_job_0">
		<text>Отримати інформацію про "випалювальника" від Рябого</text>
	</string>
	<string id="bar_lisiy_talk">
		<text>Поговорити з Лисим</text>
	</string>
	<string id="bar_lisiy_talk_0">
		<text>Поговорити зі сталкером на прізвисько "Лисий".</text>
	</string>
	<string id="bar_barman_kruglov_flash">
        <text>Врятувати дослідження вчених.</text>
    </string>
    <string id="bar_barman_kruglov_flash_0">
         <text>Необхідно не допустити попадання результатів дослідження вчених у чужі руки.</text>
    </string>
    <string id="bar_barman_kruglov_flash_1">
        <text>Отримати від професора Круглова результати досліджень.</text>
    </string>
    <string id="bar_barman_kruglov_flash_2">
        <text>Передати їх бармену в барі сталкерів.</text>
    </string>
	<string id="bar_dolg_borov_quest">
		<text>Вбити Борова та повернути вкрадену інформацію</text>
	</string>
	<string id="bar_dolg_kill_borov">
		<text>Знайти в Темній долині Борова і вбити його</text>
	</string>
	<string id="bar_dolg_info_gain">
		<text>Знайти перехоплену інформацію про лабораторію X18</text>
	</string>
	<string id="bar_dolg_return_info">
		<text>Повернути інформацію про лабораторію X18 генералу Вороніну</text>
	</string>
	<string id="bar_deserter_quest">
		<text>Вбити військовослужбовця</text>
	</string>
	<string id="bar_deserter_kill">
		<text>Вбити військового на болотах.</text>
	</string>
	<string id="bar_kill_deserter">
		<text>Вбити військового.</text>
	</string>
	<string id="bar_kill_deserter_pda">
		<text>Взяти КПК військового.</text>
	</string>
	<string id="bar_bring_pda_deserter">
		<text>Віднести КПК Бармену.</text>
	</string>
	<string id="bar_night_sniper_quest">
		<text>Таємничий снайпер.</text>
	</string>
	<string id="bar_night_sniper_quest_0">
		<text>Допомога долгівцю виконати завдання.</text>
	</string>
	<string id="bar_night_sniper_quest_1">
		<text>Вбити снайпера на вежі.</text>
	</string>
	<string id="bar_night_sniper_quest_2">
		<text>Забрати КПК снайпера.</text>
	</string>
	<string id="bar_night_sniper_quest_3">
		<text>Віднести КПК долгівцю.</text>
	</string>
